ruigi/__init__.py
ruigi/conftest.py
ruigi/backends/__init__.py
ruigi/backends/adls_gen1.py
ruigi/backends/aws.py
ruigi/backends/gcp.py
ruigi/backends/test/__init__.py
ruigi/backends/test/test_adls_gen1.py
ruigi/backends/test/utils.py
ruigi/targets/__init__.py
ruigi/targets/targets.py
ruigi/targets/test_task_target.py
ruigi/task/__init__.py
ruigi/task/dockertask.py
ruigi/task/task.py
ruigi/task/test_task.py
ruigi/task/test_utils.py
ruigi/tools/__init__.py
ruigi/tools/_tools.py
ruigi/tools/pipeline_example.py
ruigi/tools/test_tools.py
ruigi/utils/__init__.py
ruigi/utils/_utils.py
ruigi/utils/test_utils.py
ruigi/utils/hash_versioning/__init__.py
ruigi/utils/hash_versioning/hash_versioning.py
ruigi/utils/hash_versioning/inspect_bytecode.py
ruigi/utils/hash_versioning/test_hash_versioning.py
ruigi/utils/hash_versioning/tst_bytecodes_compare.py
ruigi/utils/hash_versioning/tst_bytecodes_output.py
ruigi/utils/hash_versioning/tst_hash_output.py
ruigi/viewer/__init__.py
ruigi/viewer/dash_plot.py
ruigi/viewer/viewer.py
ruigi-0.0.4.dist-info/METADATA
ruigi-0.0.4.dist-info/WHEEL
ruigi-0.0.4.dist-info/top_level.txt
ruigi-0.0.4.dist-info/RECORD
