Metadata-Version: 2.1
Name: ruigi
Version: 0.0.4
Summary: Manage your pipelines easily.
Home-page: https://github.com/datails/ruigi
Author: Datails
Author-email: 
Maintainer: Datails
License: Datails
Keywords: luigi,scheduling
Platform: UNKNOWN
Classifier: Development Status :: 3 - Alpha
Classifier: Intended Audience :: Developers
Classifier: Topic :: Software Development :: Build Tools
Classifier: License :: OSI Approved :: MIT License
Classifier: Programming Language :: Python :: 3.6
Classifier: Operating System :: OS Independent
Requires-Dist: luigi
Requires-Dist: retry
Requires-Dist: joblib
Requires-Dist: pandas
Requires-Dist: pyarrow
Provides-Extra: azure
Requires-Dist: azure-datalake-store ; extra == 'azure'
Requires-Dist: adlfs ; extra == 'azure'
Provides-Extra: complete
Requires-Dist: adlfs ; extra == 'complete'
Requires-Dist: azure-datalake-store ; extra == 'complete'
Requires-Dist: bumpversion ; extra == 'complete'
Requires-Dist: pytest ; extra == 'complete'
Requires-Dist: sphinx ; extra == 'complete'
Requires-Dist: sphinx-rtd-theme ; extra == 'complete'
Provides-Extra: dev
Requires-Dist: pytest ; extra == 'dev'
Requires-Dist: bumpversion ; extra == 'dev'
Requires-Dist: sphinx-rtd-theme ; extra == 'dev'
Requires-Dist: sphinx ; extra == 'dev'
